justpaid/__init__.py
justpaid/_version.py
justpaid/api.py
justpaid/exceptions.py
justpaid/schemas.py
justpaid-0.1.4.dist-info/LICENSE
justpaid-0.1.4.dist-info/METADATA
justpaid-0.1.4.dist-info/WHEEL
justpaid-0.1.4.dist-info/top_level.txt
justpaid-0.1.4.dist-info/RECORD
